Workbook

Sheet Mode d'emploi
A1: Comptabilité micro-entreprise — Achat / Revente
A2: Modèle de suivi : livre des recettes, registre des achats, stock et déclarations URSSAF
A4: 1. Paramètres | B4: Renseignez le nom, le SIRET, l'année et vérifiez les taux (cellules jaunes). Choisissez Oui/Non pour le versement libératoire.
A5: 2. Ventes | B5: LIVRE DES RECETTES (obligatoire) : une ligne par encaissement, dans l'ordre chronologique. Saisir le montant réellement encaissé.
A6: 3. Achats | B6: REGISTRE DES ACHATS (obligatoire pour la vente de marchandises) : une ligne par facture/justificatif d'achat, avec la catégorie.
A7: 4. Stock | B7: Suivi article par article : prix d'achat, prix de vente, marge et durée en stock. Facultatif mais très utile en achat-revente.
A8: 5. Tableau de bord | B8: Tout est calculé automatiquement : CA à déclarer par mois et par trimestre, cotisations à payer, résultat net, alertes plafonds.
A10: Code couleur | B10: Cellules jaunes / texte bleu = à remplir. Texte noir = formule, ne pas modifier. Lignes grises = exemples à effacer.
A11: Exemples | B11: Les lignes grisées dans Ventes, Achats et Stock sont des exemples : supprimez leur contenu (touche Suppr) avant de commencer.
A13: Rappels | B13: • En micro-entreprise, on déclare le CA ENCAISSÉ (pas le bénéfice) : les achats ne sont PAS déductibles des cotisations.
B14: • Conservez toutes les factures d'achat et de vente (10 ans). Une facture de vente est obligatoire pour les clients professionnels.
B15: • Vente sur plateformes (Vinted, Leboncoin, eBay…) : au-delà de 30 ventes ou 2 000 € par an, la plateforme transmet vos ventes au fisc.
B16: • Les taux et seuils de l'onglet Paramètres sont ceux connus en 2026 : vérifiez-les chaque année sur autoentrepreneur.urssaf.fr et impots.gouv.fr.
B17: • Ce fichier est une aide à la gestion et ne remplace pas l'avis d'un expert-comptable.

Sheet Paramètres
A1: Paramètres
A2: Cellules jaunes à remplir / vérifier chaque année
A3: Entreprise | E3: Listes déroulantes (modifiables)
A4: Nom de l'entreprise | B4: Mon entreprise | C4: Saisie utilisateur | E4: Plateformes / canaux | F4: Modes de paiement | G4: Catégories d'achat
A5: SIRET | B5: 000 000 000 00000 | C5: Saisie utilisateur | E5: Vinted | F5: Virement | G5: Marchandises (revente)
A6: Année comptable | B6: 2026 | C6: Toutes les synthèses filtrent sur cette année | E6: Leboncoin | F6: Carte bancaire | G6: Frais de port / emballage
A7: Périodicité de déclaration URSSAF | B7: Trimestrielle | C7: Mensuelle ou Trimestrielle (info) | E7: eBay | F7: Espèces | G7: Commissions plateformes
A8: Taux URSSAF | E8: Vente directe | F8: PayPal | G8: Matériel
A9: Taux de cotisations sociales (vente de marchandises) | B9: 0.123 | C9: Source : URSSAF, micro-entrepreneur BIC vente — 12,3 % (à vérifier chaque année) | E9: Boutique en ligne | F9: Chèque | G9: Abonnements / logiciels
A10: Option versement libératoire de l'impôt ? | B10: Non | C10: Oui / Non — option à demander à l'URSSAF, sous condition de revenu fiscal | E10: Marché / brocante | F10: Paiement plateforme | G10: Déplacements
A11: Taux versement libératoire (vente) | B11: 0.01 | C11: Source : impots.gouv.fr — 1 % du CA pour la vente de marchandises | E11: Autre | F11: Autre | G11: Publicité
A12: Contribution formation professionnelle (CFP) | B12: 0.001 | C12: Source : URSSAF — 0,1 % du CA pour un commerçant | G12: Banque / assurance
A13: Taxe pour frais de chambre consulaire (CCI) | B13: 0.00015 | C13: Source : URSSAF — 0,015 % du CA pour la vente (mettre 0 si non concerné) | G13: Autres frais
A14: Plafonds et seuils
A15: Plafond de CA micro-entreprise (vente) | B15: 203100 | C15: Plafond micro-BIC vente 2026-2028 — à vérifier sur economie.gouv.fr
A16: Seuil de franchise de TVA (vente) | B16: 85000 | C16: Franchise en base de TVA, seuil de base vente — à vérifier sur impots.gouv.fr
A17: Seuil de TVA majoré (vente) | B17: 93500 | C17: Dépassement = TVA due dès le 1er jour de dépassement

Sheet Tableau de bord
A1: ="Tableau de bord "&Paramètres!$B$6&" — "&Paramètres!$B$4 -> Tableau de bord 2026 — Mon entreprise
A2: Calculé automatiquement à partir des onglets Ventes et Achats (année choisie dans Paramètres)
E3: Montants arrondis à l'euro, comme sur la déclaration URSSAF. Achats et frais : non déductibles en micro, affichés pour calculer votre vrai bénéfice.
A4: Mois | B4: CA encaissé (à déclarer) | C4: Achats de marchandises | D4: Autres frais | E4: Cotisations sociales | F4: CFP | G4: Taxe CCI | H4: Versement libératoire | I4: Total à payer URSSAF | J4: Résultat net (après URSSAF) | K4: CA cumulé | L4: Nb de ventes
A5: =DATE(Paramètres!$B$6,1,1) -> 46023 | B5: =SUMIFS(Ventes!$H$5:$H$1004,Ventes!$A$5:$A$1004,">="&A5,Ventes!$A$5:$A$1004,"<"&DATE(YEAR(A5),MONTH(A5)+1,1)) -> 65 | C5: =SUMIFS(Achats!$G$5:$G$1004,Achats!$A$5:$A$1004,">="&A5,Achats!$A$5:$A$1004,"<"&DATE(YEAR(A5),MONTH(A5)+1,1),Achats!$E$5:$E$1004,"Marchandises (revente)") -> 20 | D5: =SUMIFS(Achats!$G$5:$G$1004,Achats!$A$5:$A$1004,">="&A5,Achats!$A$5:$A$1004,"<"&DATE(YEAR(A5),MONTH(A5)+1,1))-C5 -> 8.5 | E5: =ROUND(B5*Paramètres!$B$9,0) -> 8 | F5: =ROUND(B5*Paramètres!$B$12,0) -> 0 | G5: =ROUND(B5*Paramètres!$B$13,0) -> 0 | H5: =IF(Paramètres!$B$10="Oui",ROUND(B5*Paramètres!$B$11,0),0) -> 0 | I5: =SUM(E5:H5) -> 8 | J5: =B5-C5-D5-I5 -> 28.5 | K5: =SUM($B$5:B5) -> 65 | L5: =COUNTIFS(Ventes!$A$5:$A$1004,">="&A5,Ventes!$A$5:$A$1004,"<"&DATE(YEAR(A5),MONTH(A5)+1,1)) -> 1
A6: =DATE(Paramètres!$B$6,2,1) -> 46054 | B6: =SUMIFS(Ventes!$H$5:$H$1004,Ventes!$A$5:$A$1004,">="&A6,Ventes!$A$5:$A$1004,"<"&DATE(YEAR(A6),MONTH(A6)+1,1)) -> 0 | C6: =SUMIFS(Achats!$G$5:$G$1004,Achats!$A$5:$A$1004,">="&A6,Achats!$A$5:$A$1004,"<"&DATE(YEAR(A6),MONTH(A6)+1,1),Achats!$E$5:$E$1004,"Marchandises (revente)") -> 0 | D6: =SUMIFS(Achats!$G$5:$G$1004,Achats!$A$5:$A$1004,">="&A6,Achats!$A$5:$A$1004,"<"&DATE(YEAR(A6),MONTH(A6)+1,1))-C6 -> 0 | E6: =ROUND(B6*Paramètres!$B$9,0) -> 0 | F6: =ROUND(B6*Paramètres!$B$12,0) -> 0 | G6: =ROUND(B6*Paramètres!$B$13,0) -> 0 | H6: =IF(Paramètres!$B$10="Oui",ROUND(B6*Paramètres!$B$11,0),0) -> 0 | I6: =SUM(E6:H6) -> 0 | J6: =B6-C6-D6-I6 -> 0 | K6: =SUM($B$5:B6) -> 65 | L6: =COUNTIFS(Ventes!$A$5:$A$1004,">="&A6,Ventes!$A$5:$A$1004,"<"&DATE(YEAR(A6),MONTH(A6)+1,1)) -> 0
A7: =DATE(Paramètres!$B$6,3,1) -> 46082 | B7: =SUMIFS(Ventes!$H$5:$H$1004,Ventes!$A$5:$A$1004,">="&A7,Ventes!$A$5:$A$1004,"<"&DATE(YEAR(A7),MONTH(A7)+1,1)) -> 0 | C7: =SUMIFS(Achats!$G$5:$G$1004,Achats!$A$5:$A$1004,">="&A7,Achats!$A$5:$A$1004,"<"&DATE(YEAR(A7),MONTH(A7)+1,1),Achats!$E$5:$E$1004,"Marchandises (revente)") -> 0 | D7: =SUMIFS(Achats!$G$5:$G$1004,Achats!$A$5:$A$1004,">="&A7,Achats!$A$5:$A$1004,"<"&DATE(YEAR(A7),MONTH(A7)+1,1))-C7 -> 0 | E7: =ROUND(B7*Paramètres!$B$9,0) -> 0 | F7: =ROUND(B7*Paramètres!$B$12,0) -> 0 | G7: =ROUND(B7*Paramètres!$B$13,0) -> 0 | H7: =IF(Paramètres!$B$10="Oui",ROUND(B7*Paramètres!$B$11,0),0) -> 0 | I7: =SUM(E7:H7) -> 0 | J7: =B7-C7-D7-I7 -> 0 | K7: =SUM($B$5:B7) -> 65 | L7: =COUNTIFS(Ventes!$A$5:$A$1004,">="&A7,Ventes!$A$5:$A$1004,"<"&DATE(YEAR(A7),MONTH(A7)+1,1)) -> 0
A8: =DATE(Paramètres!$B$6,4,1) -> 46113 | B8: =SUMIFS(Ventes!$H$5:$H$1004,Ventes!$A$5:$A$1004,">="&A8,Ventes!$A$5:$A$1004,"<"&DATE(YEAR(A8),MONTH(A8)+1,1)) -> 0 | C8: =SUMIFS(Achats!$G$5:$G$1004,Achats!$A$5:$A$1004,">="&A8,Achats!$A$5:$A$1004,"<"&DATE(YEAR(A8),MONTH(A8)+1,1),Achats!$E$5:$E$1004,"Marchandises (revente)") -> 0 | D8: =SUMIFS(Achats!$G$5:$G$1004,Achats!$A$5:$A$1004,">="&A8,Achats!$A$5:$A$1004,"<"&DATE(YEAR(A8),MONTH(A8)+1,1))-C8 -> 0 | E8: =ROUND(B8*Paramètres!$B$9,0) -> 0 | F8: =ROUND(B8*Paramètres!$B$12,0) -> 0 | G8: =ROUND(B8*Paramètres!$B$13,0) -> 0 | H8: =IF(Paramètres!$B$10="Oui",ROUND(B8*Paramètres!$B$11,0),0) -> 0 | I8: =SUM(E8:H8) -> 0 | J8: =B8-C8-D8-I8 -> 0 | K8: =SUM($B$5:B8) -> 65 | L8: =COUNTIFS(Ventes!$A$5:$A$1004,">="&A8,Ventes!$A$5:$A$1004,"<"&DATE(YEAR(A8),MONTH(A8)+1,1)) -> 0
A9: =DATE(Paramètres!$B$6,5,1) -> 46143 | B9: =SUMIFS(Ventes!$H$5:$H$1004,Ventes!$A$5:$A$1004,">="&A9,Ventes!$A$5:$A$1004,"<"&DATE(YEAR(A9),MONTH(A9)+1,1)) -> 0 | C9: =SUMIFS(Achats!$G$5:$G$1004,Achats!$A$5:$A$1004,">="&A9,Achats!$A$5:$A$1004,"<"&DATE(YEAR(A9),MONTH(A9)+1,1),Achats!$E$5:$E$1004,"Marchandises (revente)") -> 0 | D9: =SUMIFS(Achats!$G$5:$G$1004,Achats!$A$5:$A$1004,">="&A9,Achats!$A$5:$A$1004,"<"&DATE(YEAR(A9),MONTH(A9)+1,1))-C9 -> 0 | E9: =ROUND(B9*Paramètres!$B$9,0) -> 0 | F9: =ROUND(B9*Paramètres!$B$12,0) -> 0 | G9: =ROUND(B9*Paramètres!$B$13,0) -> 0 | H9: =IF(Paramètres!$B$10="Oui",ROUND(B9*Paramètres!$B$11,0),0) -> 0 | I9: =SUM(E9:H9) -> 0 | J9: =B9-C9-D9-I9 -> 0 | K9: =SUM($B$5:B9) -> 65 | L9: =COUNTIFS(Ventes!$A$5:$A$1004,">="&A9,Ventes!$A$5:$A$1004,"<"&DATE(YEAR(A9),MONTH(A9)+1,1)) -> 0
A10: =DATE(Paramètres!$B$6,6,1) -> 46174 | B10: =SUMIFS(Ventes!$H$5:$H$1004,Ventes!$A$5:$A$1004,">="&A10,Ventes!$A$5:$A$1004,"<"&DATE(YEAR(A10),MONTH(A10)+1,1)) -> 0 | C10: =SUMIFS(Achats!$G$5:$G$1004,Achats!$A$5:$A$1004,">="&A10,Achats!$A$5:$A$1004,"<"&DATE(YEAR(A10),MONTH(A10)+1,1),Achats!$E$5:$E$1004,"Marchandises (revente)") -> 0 | D10: =SUMIFS(Achats!$G$5:$G$1004,Achats!$A$5:$A$1004,">="&A10,Achats!$A$5:$A$1004,"<"&DATE(YEAR(A10),MONTH(A10)+1,1))-C10 -> 0 | E10: =ROUND(B10*Paramètres!$B$9,0) -> 0 | F10: =ROUND(B10*Paramètres!$B$12,0) -> 0 | G10: =ROUND(B10*Paramètres!$B$13,0) -> 0 | H10: =IF(Paramètres!$B$10="Oui",ROUND(B10*Paramètres!$B$11,0),0) -> 0 | I10: =SUM(E10:H10) -> 0 | J10: =B10-C10-D10-I10 -> 0 | K10: =SUM($B$5:B10) -> 65 | L10: =COUNTIFS(Ventes!$A$5:$A$1004,">="&A10,Ventes!$A$5:$A$1004,"<"&DATE(YEAR(A10),MONTH(A10)+1,1)) -> 0
A11: =DATE(Paramètres!$B$6,7,1) -> 46204 | B11: =SUMIFS(Ventes!$H$5:$H$1004,Ventes!$A$5:$A$1004,">="&A11,Ventes!$A$5:$A$1004,"<"&DATE(YEAR(A11),MONTH(A11)+1,1)) -> 0 | C11: =SUMIFS(Achats!$G$5:$G$1004,Achats!$A$5:$A$1004,">="&A11,Achats!$A$5:$A$1004,"<"&DATE(YEAR(A11),MONTH(A11)+1,1),Achats!$E$5:$E$1004,"Marchandises (revente)") -> 0 | D11: =SUMIFS(Achats!$G$5:$G$1004,Achats!$A$5:$A$1004,">="&A11,Achats!$A$5:$A$1004,"<"&DATE(YEAR(A11),MONTH(A11)+1,1))-C11 -> 0 | E11: =ROUND(B11*Paramètres!$B$9,0) -> 0 | F11: =ROUND(B11*Paramètres!$B$12,0) -> 0 | G11: =ROUND(B11*Paramètres!$B$13,0) -> 0 | H11: =IF(Paramètres!$B$10="Oui",ROUND(B11*Paramètres!$B$11,0),0) -> 0 | I11: =SUM(E11:H11) -> 0 | J11: =B11-C11-D11-I11 -> 0 | K11: =SUM($B$5:B11) -> 65 | L11: =COUNTIFS(Ventes!$A$5:$A$1004,">="&A11,Ventes!$A$5:$A$1004,"<"&DATE(YEAR(A11),MONTH(A11)+1,1)) -> 0
A12: =DATE(Paramètres!$B$6,8,1) -> 46235 | B12: =SUMIFS(Ventes!$H$5:$H$1004,Ventes!$A$5:$A$1004,">="&A12,Ventes!$A$5:$A$1004,"<"&DATE(YEAR(A12),MONTH(A12)+1,1)) -> 0 | C12: =SUMIFS(Achats!$G$5:$G$1004,Achats!$A$5:$A$1004,">="&A12,Achats!$A$5:$A$1004,"<"&DATE(YEAR(A12),MONTH(A12)+1,1),Achats!$E$5:$E$1004,"Marchandises (revente)") -> 0 | D12: =SUMIFS(Achats!$G$5:$G$1004,Achats!$A$5:$A$1004,">="&A12,Achats!$A$5:$A$1004,"<"&DATE(YEAR(A12),MONTH(A12)+1,1))-C12 -> 0 | E12: =ROUND(B12*Paramètres!$B$9,0) -> 0 | F12: =ROUND(B12*Paramètres!$B$12,0) -> 0 | G12: =ROUND(B12*Paramètres!$B$13,0) -> 0 | H12: =IF(Paramètres!$B$10="Oui",ROUND(B12*Paramètres!$B$11,0),0) -> 0 | I12: =SUM(E12:H12) -> 0 | J12: =B12-C12-D12-I12 -> 0 | K12: =SUM($B$5:B12) -> 65 | L12: =COUNTIFS(Ventes!$A$5:$A$1004,">="&A12,Ventes!$A$5:$A$1004,"<"&DATE(YEAR(A12),MONTH(A12)+1,1)) -> 0
A13: =DATE(Paramètres!$B$6,9,1) -> 46266 | B13: =SUMIFS(Ventes!$H$5:$H$1004,Ventes!$A$5:$A$1004,">="&A13,Ventes!$A$5:$A$1004,"<"&DATE(YEAR(A13),MONTH(A13)+1,1)) -> 0 | C13: =SUMIFS(Achats!$G$5:$G$1004,Achats!$A$5:$A$1004,">="&A13,Achats!$A$5:$A$1004,"<"&DATE(YEAR(A13),MONTH(A13)+1,1),Achats!$E$5:$E$1004,"Marchandises (revente)") -> 0 | D13: =SUMIFS(Achats!$G$5:$G$1004,Achats!$A$5:$A$1004,">="&A13,Achats!$A$5:$A$1004,"<"&DATE(YEAR(A13),MONTH(A13)+1,1))-C13 -> 0 | E13: =ROUND(B13*Paramètres!$B$9,0) -> 0 | F13: =ROUND(B13*Paramètres!$B$12,0) -> 0 | G13: =ROUND(B13*Paramètres!$B$13,0) -> 0 | H13: =IF(Paramètres!$B$10="Oui",ROUND(B13*Paramètres!$B$11,0),0) -> 0 | I13: =SUM(E13:H13) -> 0 | J13: =B13-C13-D13-I13 -> 0 | K13: =SUM($B$5:B13) -> 65 | L13: =COUNTIFS(Ventes!$A$5:$A$1004,">="&A13,Ventes!$A$5:$A$1004,"<"&DATE(YEAR(A13),MONTH(A13)+1,1)) -> 0
A14: =DATE(Paramètres!$B$6,10,1) -> 46296 | B14: =SUMIFS(Ventes!$H$5:$H$1004,Ventes!$A$5:$A$1004,">="&A14,Ventes!$A$5:$A$1004,"<"&DATE(YEAR(A14),MONTH(A14)+1,1)) -> 0 | C14: =SUMIFS(Achats!$G$5:$G$1004,Achats!$A$5:$A$1004,">="&A14,Achats!$A$5:$A$1004,"<"&DATE(YEAR(A14),MONTH(A14)+1,1),Achats!$E$5:$E$1004,"Marchandises (revente)") -> 0 | D14: =SUMIFS(Achats!$G$5:$G$1004,Achats!$A$5:$A$1004,">="&A14,Achats!$A$5:$A$1004,"<"&DATE(YEAR(A14),MONTH(A14)+1,1))-C14 -> 0 | E14: =ROUND(B14*Paramètres!$B$9,0) -> 0 | F14: =ROUND(B14*Paramètres!$B$12,0) -> 0 | G14: =ROUND(B14*Paramètres!$B$13,0) -> 0 | H14: =IF(Paramètres!$B$10="Oui",ROUND(B14*Paramètres!$B$11,0),0) -> 0 | I14: =SUM(E14:H14) -> 0 | J14: =B14-C14-D14-I14 -> 0 | K14: =SUM($B$5:B14) -> 65 | L14: =COUNTIFS(Ventes!$A$5:$A$1004,">="&A14,Ventes!$A$5:$A$1004,"<"&DATE(YEAR(A14),MONTH(A14)+1,1)) -> 0
A15: =DATE(Paramètres!$B$6,11,1) -> 46327 | B15: =SUMIFS(Ventes!$H$5:$H$1004,Ventes!$A$5:$A$1004,">="&A15,Ventes!$A$5:$A$1004,"<"&DATE(YEAR(A15),MONTH(A15)+1,1)) -> 0 | C15: =SUMIFS(Achats!$G$5:$G$1004,Achats!$A$5:$A$1004,">="&A15,Achats!$A$5:$A$1004,"<"&DATE(YEAR(A15),MONTH(A15)+1,1),Achats!$E$5:$E$1004,"Marchandises (revente)") -> 0 | D15: =SUMIFS(Achats!$G$5:$G$1004,Achats!$A$5:$A$1004,">="&A15,Achats!$A$5:$A$1004,"<"&DATE(YEAR(A15),MONTH(A15)+1,1))-C15 -> 0 | E15: =ROUND(B15*Paramètres!$B$9,0) -> 0 | F15: =ROUND(B15*Paramètres!$B$12,0) -> 0 | G15: =ROUND(B15*Paramètres!$B$13,0) -> 0 | H15: =IF(Paramètres!$B$10="Oui",ROUND(B15*Paramètres!$B$11,0),0) -> 0 | I15: =SUM(E15:H15) -> 0 | J15: =B15-C15-D15-I15 -> 0 | K15: =SUM($B$5:B15) -> 65 | L15: =COUNTIFS(Ventes!$A$5:$A$1004,">="&A15,Ventes!$A$5:$A$1004,"<"&DATE(YEAR(A15),MONTH(A15)+1,1)) -> 0
A16: =DATE(Paramètres!$B$6,12,1) -> 46357 | B16: =SUMIFS(Ventes!$H$5:$H$1004,Ventes!$A$5:$A$1004,">="&A16,Ventes!$A$5:$A$1004,"<"&DATE(YEAR(A16),MONTH(A16)+1,1)) -> 0 | C16: =SUMIFS(Achats!$G$5:$G$1004,Achats!$A$5:$A$1004,">="&A16,Achats!$A$5:$A$1004,"<"&DATE(YEAR(A16),MONTH(A16)+1,1),Achats!$E$5:$E$1004,"Marchandises (revente)") -> 0 | D16: =SUMIFS(Achats!$G$5:$G$1004,Achats!$A$5:$A$1004,">="&A16,Achats!$A$5:$A$1004,"<"&DATE(YEAR(A16),MONTH(A16)+1,1))-C16 -> 0 | E16: =ROUND(B16*Paramètres!$B$9,0) -> 0 | F16: =ROUND(B16*Paramètres!$B$12,0) -> 0 | G16: =ROUND(B16*Paramètres!$B$13,0) -> 0 | H16: =IF(Paramètres!$B$10="Oui",ROUND(B16*Paramètres!$B$11,0),0) -> 0 | I16: =SUM(E16:H16) -> 0 | J16: =B16-C16-D16-I16 -> 0 | K16: =SUM($B$5:B16) -> 65 | L16: =COUNTIFS(Ventes!$A$5:$A$1004,">="&A16,Ventes!$A$5:$A$1004,"<"&DATE(YEAR(A16),MONTH(A16)+1,1)) -> 0
A17: TOTAL | B17: =SUM(B5:B16) -> 65 | C17: =SUM(C5:C16) -> 20 | D17: =SUM(D5:D16) -> 8.5 | E17: =SUM(E5:E16) -> 8 | F17: =SUM(F5:F16) -> 0 | G17: =SUM(G5:G16) -> 0 | H17: =SUM(H5:H16) -> 0 | I17: =SUM(I5:I16) -> 8 | J17: =SUM(J5:J16) -> 28.5 | L17: =SUM(L5:L16) -> 1
A19: Déclarations trimestrielles | F19: Indicateurs annuels
A20: Trimestre | B20: CA à déclarer | C20: À payer URSSAF | D20: Date limite | F20: CA encaissé de l'année | J20: =B17 -> 65
A21: T1 (janv.–mars) | B21: =SUM(B5:B7) -> 65 | C21: =SUM(I5:I7) -> 8 | D21: =DATE(Paramètres!$B$6,4,30) -> 46142 | F21: Marge brute (CA − achats marchandises) | J21: =B17-C17 -> 45
A22: T2 (avr.–juin) | B22: =SUM(B8:B10) -> 0 | C22: =SUM(I8:I10) -> 0 | D22: =DATE(Paramètres!$B$6,7,31) -> 46234 | F22: Taux de marge brute | J22: =IFERROR((B17-C17)/B17,0) -> 0.69230769
A23: T3 (juil.–sept.) | B23: =SUM(B11:B13) -> 0 | C23: =SUM(I11:I13) -> 0 | D23: =DATE(Paramètres!$B$6,10,31) -> 46326 | F23: Bénéfice net estimé (après frais et URSSAF) | J23: =J17 -> 28.5
A24: T4 (oct.–déc.) | B24: =SUM(B14:B16) -> 0 | C24: =SUM(I14:I16) -> 0 | D24: =DATE(Paramètres!$B$6+1,1,31) -> 46418 | F24: Plafond micro-entreprise utilisé | J24: =IFERROR(B17/Paramètres!$B$15,0) -> 0.00032003939
A25: Déclaration mensuelle : CA du mois, à déclarer avant la fin du mois suivant (voir tableau ci-dessus). | F25: Reste avant seuil de franchise TVA | J25: =Paramètres!$B$16-B17 -> 84935
F26: Statut | J26: =IF(B17>Paramètres!$B$15,"⚠ Plafond micro dépassé",IF(B17>Paramètres!$B$17,"⚠ TVA due (seuil majoré dépassé)",IF(B17>Paramètres!$B$16,"⚠ Seuil TVA de base dépassé — surveiller",IF(B17>0.8*Paramètres!$B$16,"Attention : 80 % du seuil TVA atteint","✔ OK")))) -> ✔ OK

Sheet Ventes
A1: Livre des recettes
A2: Une ligne par encaissement, par ordre chronologique — montant réellement encaissé | G2: Total encaissé (toutes années) : | H2: =SUM(H5:H1004) -> 65
A4: Date d'encaissement | B4: N° facture | C4: Client | D4: Article / description | E4: Réf. stock | F4: Plateforme / canal | G4: Mode de paiement | H4: Montant encaissé (€) | I4: Commentaire
A5: 46034 | B5: F2026-001 | C5: Marie D. | D5: Veste en cuir vintage | E5: A001 | F5: Vinted | G5: Paiement plateforme | H5: 65 | I5: Exemple — à effacer

Sheet Achats
A1: Registre des achats
A2: Une ligne par facture ou justificatif d'achat — conservez les pièces justificatives | F2: Total achats (toutes années) : | G2: =SUM(G5:G1004) -> 28.5
A4: Date | B4: Fournisseur / vendeur | C4: N° facture / justificatif | D4: Description | E4: Catégorie | F4: Mode de paiement | G4: Montant payé TTC (€) | H4: Commentaire
A5: 46027 | B5: Particulier (Leboncoin) | C5: Capture annonce | D5: Veste en cuir vintage | E5: Marchandises (revente) | F5: Espèces | G5: 20 | H5: Exemple — à effacer
A6: 46030 | B6: La Poste | C6: Reçu 1234 | D6: Enveloppes et cartons | E6: Frais de port / emballage | F6: Carte bancaire | G6: 8.5 | H6: Exemple — à effacer

Sheet Stock
A1: Suivi du stock et des marges
A2: Un article par ligne — les colonnes blanches se calculent seules
A3: Articles en stock | C3: =COUNTIF(L7:L1006,"En stock") -> 1 | D3: Valeur du stock (achat) | F3: =SUMIFS(F7:F1006,L7:L1006,"En stock")+SUMIFS(G7:G1006,L7:L1006,"En stock") -> 8 | G3: Articles vendus | H3: =COUNTIF(L7:L1006,"Vendu") -> 1 | I3: Marge nette totale | J3: =SUM(M7:M1006) -> 37.5 | K3: Marge moyenne | M3: =IFERROR(SUM(M7:M1006)/SUMIFS(J7:J1006,L7:L1006,"Vendu"),0) -> 0.57692308
A4: Jours en stock en rouge = article invendu depuis plus de 90 jours. Frais de vente = commission plateforme + port payé par vous.
A6: Réf. | B6: Article | C6: Catégorie / type | D6: Date d'achat | E6: Lieu / fournisseur | F6: Prix d'achat (€) | G6: Frais avant vente (€) | H6: Prix affiché (€) | I6: Date de vente | J6: Prix de vente (€) | K6: Frais de vente (€) | L6: Statut | M6: Marge nette (€) | N6: Marge % | O6: Jours en stock
A7: A001 | B7: Veste en cuir vintage | C7: Vêtement | D7: 46027 | E7: Leboncoin | F7: 20 | G7: 3 | H7: 70 | I7: 46034 | J7: 65 | K7: 4.5 | L7: =IF(A7="","",IF(I7<>"","Vendu","En stock")) -> Vendu | M7: =IF(J7="","",J7-F7-G7-K7) -> 37.5 | N7: =IF(OR(J7="",J7=0),"",M7/J7) -> 0.57692308 | O7: =IF(D7="","",IF(I7<>"",I7,TODAY())-D7) -> 7
A8: A002 | B8: Lampe de bureau années 70 | C8: Déco | D8: 46042 | E8: Brocante | F8: 8 | G8: 0 | H8: 35 | L8: =IF(A8="","",IF(I8<>"","Vendu","En stock")) -> En stock | M8: =IF(J8="","",J8-F8-G8-K8) | N8: =IF(OR(J8="",J8=0),"",M8/J8) | O8: =IF(D8="","",IF(I8<>"",I8,TODAY())-D8) -> 259
L9: =IF(A9="","",IF(I9<>"","Vendu","En stock")) | M9: =IF(J9="","",J9-F9-G9-K9) | N9: =IF(OR(J9="",J9=0),"",M9/J9) | O9: =IF(D9="","",IF(I9<>"",I9,TODAY())-D9)
L10: =IF(A10="","",IF(I10<>"","Vendu","En stock")) | M10: =IF(J10="","",J10-F10-G10-K10) | N10: =IF(OR(J10="",J10=0),"",M10/J10) | O10: =IF(D10="","",IF(I10<>"",I10,TODAY())-D10)
L11: =IF(A11="","",IF(I11<>"","Vendu","En stock")) | M11: =IF(J11="","",J11-F11-G11-K11) | N11: =IF(OR(J11="",J11=0),"",M11/J11) | O11: =IF(D11="","",IF(I11<>"",I11,TODAY())-D11)
L12: =IF(A12="","",IF(I12<>"","Vendu","En stock")) | M12: =IF(J12="","",J12-F12-G12-K12) | N12: =IF(OR(J12="",J12=0),"",M12/J12) | O12: =IF(D12="","",IF(I12<>"",I12,TODAY())-D12)
L13: =IF(A13="","",IF(I13<>"","Vendu","En stock")) | M13: =IF(J13="","",J13-F13-G13-K13) | N13: =IF(OR(J13="",J13=0),"",M13/J13) | O13: =IF(D13="","",IF(I13<>"",I13,TODAY())-D13)
L14: =IF(A14="","",IF(I14<>"","Vendu","En stock")) | M14: =IF(J14="","",J14-F14-G14-K14) | N14: =IF(OR(J14="",J14=0),"",M14/J14) | O14: =IF(D14="","",IF(I14<>"",I14,TODAY())-D14)
L15: =IF(A15="","",IF(I15<>"","Vendu","En stock")) | M15: =IF(J15="","",J15-F15-G15-K15) | N15: =IF(OR(J15="",J15=0),"",M15/J15) | O15: =IF(D15="","",IF(I15<>"",I15,TODAY())-D15)
L16: =IF(A16="","",IF(I16<>"","Vendu","En stock")) | M16: =IF(J16="","",J16-F16-G16-K16) | N16: =IF(OR(J16="",J16=0),"",M16/J16) | O16: =IF(D16="","",IF(I16<>"",I16,TODAY())-D16)
L17: =IF(A17="","",IF(I17<>"","Vendu","En stock")) | M17: =IF(J17="","",J17-F17-G17-K17) | N17: =IF(OR(J17="",J17=0),"",M17/J17) | O17: =IF(D17="","",IF(I17<>"",I17,TODAY())-D17)
L18: =IF(A18="","",IF(I18<>"","Vendu","En stock")) | M18: =IF(J18="","",J18-F18-G18-K18) | N18: =IF(OR(J18="",J18=0),"",M18/J18) | O18: =IF(D18="","",IF(I18<>"",I18,TODAY())-D18)
L19: =IF(A19="","",IF(I19<>"","Vendu","En stock")) | M19: =IF(J19="","",J19-F19-G19-K19) | N19: =IF(OR(J19="",J19=0),"",M19/J19) | O19: =IF(D19="","",IF(I19<>"",I19,TODAY())-D19)
L20: =IF(A20="","",IF(I20<>"","Vendu","En stock")) | M20: =IF(J20="","",J20-F20-G20-K20) | N20: =IF(OR(J20="",J20=0),"",M20/J20) | O20: =IF(D20="","",IF(I20<>"",I20,TODAY())-D20)
... L1006: =IF(A1006="","",IF(I1006<>"","Vendu","En stock")) | M1006: =IF(J1006="","",J1006-F1006-G1006-K1006) | N1006: =IF(OR(J1006="",J1006=0),"",M1006/J1006) | O1006: =IF(D1006="","",IF(I1006<>"",I1006,TODAY())-D1006)
